setup.py
django_restapi/__init__.py
django_restapi/authentication.py
django_restapi/model_resource.py
django_restapi/receiver.py
django_restapi/resource.py
django_restapi/responder.py
django_restapi/sites.py
django_restapi/templates/rest/api_index.html
django_restapi/templates/rest/base.html
django_restapi/templates/rest/index.html
django_restapi_op.egg-info/PKG-INFO
django_restapi_op.egg-info/SOURCES.txt
django_restapi_op.egg-info/dependency_links.txt
django_restapi_op.egg-info/not-zip-safe
django_restapi_op.egg-info/requires.txt
django_restapi_op.egg-info/top_level.txt