Metadata-Version: 1.0
Name: django-restapi-op
Version: 0.1.0
Summary: Django REST API modified for OpenProximity
Home-page: https://github.com/OpenProximity/django_restapi
Author: Naranjo Manuel Francisco
Author-email: manuel@aircable.net
License: Apache V2
Platform: UNKNOWN
